tests/__init__.py
tests/test_amazon.py
tests/test_conversion.py
tests/test_convert_viraloverlay.py
tests/test_google.py
transcript_processing/__init__.py
transcript_processing/config.py
transcript_processing/converter.py
transcript_processing/helpers.py
transcript_processing/outputs.py
transcript_processing/tpro.py
transcript_processing/converters/__init__.py
transcript_processing/converters/amazon.py
transcript_processing/converters/gentle.py
transcript_processing/converters/google.py
transcript_processing/converters/speechmatics.py
tpro-0.15.dist-info/METADATA
tpro-0.15.dist-info/WHEEL
tpro-0.15.dist-info/entry_points.txt
tpro-0.15.dist-info/top_level.txt
tpro-0.15.dist-info/RECORD
