Metadata-Version: 2.1
Name: tpro
Version: 0.15
Summary: tpro processes transcripts from speech-to-text services and outputs to various formats.
Home-page: https://github.com/zevaverbach/tpro
License: UNKNOWN
Platform: UNKNOWN
Requires-Dist: Click
Requires-Dist: nltk
